cis_web/__init__.py
cis_web/_version.py
cis_web/chan_info_sys_mockups.py
cis_web/cis.py
cis_web/monitor_gunicorn.py
channel_information_system-0.0.3.dist-info/LICENSE
channel_information_system-0.0.3.dist-info/METADATA
channel_information_system-0.0.3.dist-info/WHEEL
channel_information_system-0.0.3.dist-info/entry_points.txt
channel_information_system-0.0.3.dist-info/top_level.txt
channel_information_system-0.0.3.dist-info/RECORD
