Metadata-Version: 2.1
Name: channel_information_system
Version: 0.0.3
Summary: A collection of small programs to work with lots of video files
Author-email: Joseph Areeda <joe@areeda.com>
Maintainer-email: Joseph Areeda <joe@areeda.com>
Classifier: Development Status :: 3 - Alpha
Classifier: Environment :: Console
Classifier: Environment :: Web Environment
Classifier: Framework :: Flask
Classifier: Intended Audience :: Developers
Classifier: Intended Audience :: End Users/Desktop
Classifier: License :: OSI Approved :: GNU General Public License v3 or later (GPLv3+)
Classifier: Natural Language :: English
Classifier: Operating System :: POSIX
Classifier: Operating System :: Unix
Classifier: Operating System :: MacOS
Classifier: Programming Language :: Python
Classifier: Programming Language :: Python :: 3
Classifier: Programming Language :: Python :: 3.9
Classifier: Programming Language :: Python :: 3.10
Classifier: Programming Language :: Python :: 3.11
Classifier: Topic :: Multimedia
Requires-Python: >=3.9
License-File: LICENSE
Requires-Dist: flask
Requires-Dist: gunicorn
Requires-Dist: numpy
Requires-Dist: ja-webutils
Requires-Dist: psutil
